nova_playlist/__init__.py
nova_playlist/cli.py
nova_playlist/nova.py
nova_playlist/parser.py
nova_playlist-0.4.0.dist-info/LICENSE.txt
nova_playlist-0.4.0.dist-info/METADATA
nova_playlist-0.4.0.dist-info/WHEEL
nova_playlist-0.4.0.dist-info/entry_points.txt
nova_playlist-0.4.0.dist-info/RECORD
