Metadata-Version: 2.1
Name: nova-playlist
Version: 0.4.0
Summary: Display information about the songs that recently played on Radio Nova
Home-page: https://github.com/rafikdraoui/nova-playlist
License: MIT
Author: Rafik Draoui
Author-email: rafik@rafik.ca
Requires-Python: >=3.9,<4.0
Classifier: License :: OSI Approved :: MIT License
Classifier: Programming Language :: Python :: 3
Classifier: Programming Language :: Python :: 3.9
Classifier: Programming Language :: Python :: 3.10
Classifier: Programming Language :: Python :: 3.11
Project-URL: Repository, https://github.com/rafikdraoui/nova-playlist
